{
  "data": {
    "confidentialityDisclaimer": {
      "confidentialityChecksChecked": [
        "confidentialityChecksChecked"
      ]
    },
    "applicantSolicitorEmailAddress": "fprl_caseworker_solicitor@mailinator.com",
    "caseworkerEmailAddress": "prl_caseworker_solicitor@mailinator.com",
    "solicitorName": "${C100SolicitorName}",
    "payAgreeStatement": [
      "agree"
    ],
    "feeAmount": "232.00",
    "isEngDocGen": null,
    "submitAndPayDownloadApplicationWelshLink": null,
    "submitAndPayDownloadApplicationLink": {
      "document_url": "${DocumentUrl}",
      "document_binary_url": "${DocumentUrl}/binary",
      "document_filename": "${DocumentFileName}",
      "document_hash": "${DocumentHash}"
    },
    "isWelshDocGen": null,
    "paymentServiceRequestReferenceNumber": "${paymentReferenceNumber}"
  },
  "event": {
    "id": "submitAndPay",
    "summary": "",
    "description": ""
  },
  "event_token": "${event_token}",
  "ignore_warning": false
}